django_auditable_model/__init__.py
django_auditable_model/admin.py
django_auditable_model/apps.py
django_auditable_model/models.py
django_auditable_model/serializers.py
django_auditable_model/tests.py
django_auditable_model/views.py
django_auditable_model/migrations/__init__.py
django_auditable_model-0.1.4.dist-info/METADATA
django_auditable_model-0.1.4.dist-info/WHEEL
django_auditable_model-0.1.4.dist-info/top_level.txt
django_auditable_model-0.1.4.dist-info/RECORD
